MANIFEST.in
requirements-dev.txt
requirements.txt
setup.py
test/test_base.py
test/test_blocks.py
test/test_images.py
test/test_images_io.py
test/test_readers.py
test/test_series.py
test/test_series_io.py
thunder/__init__.py
thunder/base.py
thunder/readers.py
thunder/utils.py
thunder/writers.py
thunder/blocks/__init__.py
thunder/blocks/blocks.py
thunder/blocks/local.py
thunder/images/__init__.py
thunder/images/images.py
thunder/images/readers.py
thunder/images/writers.py
thunder/series/__init__.py
thunder/series/readers.py
thunder/series/series.py
thunder/series/writers.py
thunder_python.egg-info/PKG-INFO
thunder_python.egg-info/SOURCES.txt
thunder_python.egg-info/dependency_links.txt
thunder_python.egg-info/requires.txt
thunder_python.egg-info/top_level.txt