Metadata-Version: 1.0
Name: thunder-python
Version: 1.2.0
Summary: large-scale image and time series analysis
Home-page: https://github.com/thunder-project/thunder
Author: freeman-lab
Author-email: the.freeman.lab@gmail.com
License: UNKNOWN
Platform: UNKNOWN
